openquake/gem_taxonomy/__init__.py
openquake/gem_taxonomy/classes.py
openquake/gem_taxonomy/scripts.py
openquake/gem_taxonomy/version.py
openquake/gem_taxonomy/test/validate_test.py
openquake_gem_taxonomy-1.11.3.dist-info/licenses/LICENSE
openquake_gem_taxonomy-1.11.3.dist-info/METADATA
openquake_gem_taxonomy-1.11.3.dist-info/WHEEL
openquake_gem_taxonomy-1.11.3.dist-info/entry_points.txt
openquake_gem_taxonomy-1.11.3.dist-info/top_level.txt
openquake_gem_taxonomy-1.11.3.dist-info/RECORD
