Metadata-Version: 2.4
Name: openquake.gem-taxonomy
Version: 1.11.3
Summary: Openquake Gem Taxonomy - Package to manage GEM Building Taxonomy strings
Author-email: Matteo Nastasi <nastasi@openquake.org>
Maintainer-email: Matteo Nastasi <nastasi@openquake.org>
Project-URL: Repository, https://github.com/gem/oq-gem-taxonomy
Project-URL: Bug Tracker, https://github.com/gem/oq-gem-taxonomy/issues
Keywords: GEM,taxonomy,building,standard,openquake
Classifier: Development Status :: 4 - Beta
Classifier: Programming Language :: Python
Requires-Python: >=3
License-File: LICENSE
Requires-Dist: openquake.gem-taxonomy-data~=1.4
Requires-Dist: parsimonious==0.10.0
Provides-Extra: test
Requires-Dist: flake8; extra == "test"
Requires-Dist: pytest==8.3.3; extra == "test"
Requires-Dist: pytest-cov==6.0.0; extra == "test"
Dynamic: license-file
